yong_wechat/__init__.py
yong_wechat-23.11.61.dist-info/METADATA
yong_wechat-23.11.61.dist-info/WHEEL
yong_wechat-23.11.61.dist-info/entry_points.txt
yong_wechat-23.11.61.dist-info/top_level.txt
yong_wechat-23.11.61.dist-info/RECORD
