Metadata-Version: 2.1
Name: yong-wechat
Version: 23.11.61
Summary: yong_wechat
Home-page: https://github.com/chenyongze
Author: yongze
Author-email: yongze@dingtalk.com
License: MIT
Keywords: yong,utils
